{
  "project_info": {
    "project_number": "237371250570",
    "project_id": "notification-63b67",
    "storage_bucket": "notification-63b67.firebasestorage.app"
  },
  "client": [
    {
      "client_info": {
        "mobilesdk_app_id": "1:237371250570:android:7b9b7605550a62796c1a73",
        "android_client_info": {
          "package_name": "com.example.praktikumfc"
        }
      },
      "oauth_client": [],
      "api_key": [
        {
          "current_key": "AIzaSyBXyqMlS7BfJ_GZjHONVy1_mHjusfRNou4"
        }
      ],
      "services": {
        "appinvite_service": {
          "other_platform_oauth_client": []
        }
      }
    }
  ],
  "configuration_version": "1"
}